{
  "activity": 61697,
  "add-appointment": 61698,
  "add-file": 61699,
  "add-note": 61700,
  "add-o": 61701,
  "add-thin": 61702,
  "add": 61703,
  "addcard": 61704,
  "afternoon": 61705,
  "analytics": 61706,
  "anchor": 61707,
  "appointment": 61708,
  "archive": 61709,
  "arrow-down": 61710,
  "arrow-left-h": 61711,
  "arrow-left": 61712,
  "arrow-right-h": 61713,
  "arrow-right": 61714,
  "arrow-up": 61715,
  "attach": 61716,
  "back-office": 61717,
  "beaker": 61718,
  "bell": 61719,
  "billable-charge": 61720,
  "board": 61721,
  "bolt": 61722,
  "book": 61723,
  "bookmark-o": 61724,
  "bookmark": 61725,
  "bot": 61726,
  "box-check-o": 61727,
  "box-check": 61728,
  "box-empty": 61729,
  "box-minus-o": 61730,
  "box-minus": 61731,
  "box-plus-o": 61732,
  "box-plus": 61733,
  "box-times-o": 61734,
  "box-times": 61735,
  "bug": 61736,
  "bull": 61737,
  "calculator": 61738,
  "calendar": 61739,
  "camera": 61740,
  "candidate-circle": 61741,
  "candidate": 61742,
  "canvas": 61743,
  "card-expand": 61744,
  "category-tags": 61745,
  "caution-o": 61746,
  "caution-triangle-o": 61747,
  "caution": 61748,
  "certification": 61749,
  "chart-bar": 61750,
  "chart-donut": 61751,
  "chart-funnel": 61752,
  "chart-line": 61753,
  "chart-pie-o": 61754,
  "chart-pie": 61755,
  "check-circle-filled": 61756,
  "check-circle": 61757,
  "check-o": 61758,
  "check": 61759,
  "checkbox-add": 61760,
  "checkbox-empty": 61761,
  "checkbox-filled": 61762,
  "checkbox-indeterminate": 61763,
  "circle-o": 61764,
  "circle": 61765,
  "clipboard": 61766,
  "clock-arrow": 61767,
  "clock": 61768,
  "close-o": 61769,
  "close": 61770,
  "coffee": 61771,
  "collapse": 61772,
  "columns": 61773,
  "comment-o": 61774,
  "comment": 61775,
  "commission": 61776,
  "company-circle": 61777,
  "company": 61778,
  "compass": 61779,
  "complex": 61780,
  "configure-o": 61781,
  "configure": 61782,
  "convert": 61783,
  "crane": 61784,
  "credential": 61785,
  "crf": 61786,
  "crown": 61787,
  "custom-objects": 61788,
  "dashboard-o": 61789,
  "dashboard": 61790,
  "day": 61791,
  "delete-o": 61792,
  "delete": 61793,
  "department": 61794,
  "desktop": 61795,
  "download": 61796,
  "dropzone": 61797,
  "duplicate": 61798,
  "earn-code-template": 61799,
  "earn-code": 61800,
  "edit-circle-filled": 61801,
  "edit-circle": 61802,
  "edit-o": 61803,
  "edit": 61804,
  "education": 61805,
  "email-autoadd": 61806,
  "email-invoice-template": 61807,
  "email": 61808,
  "engagement": 61809,
  "evening": 61810,
  "expand": 61811,
  "expense": 61812,
  "export-html": 61813,
  "export-ms": 61814,
  "external-open": 61815,
  "external": 61816,
  "facebook-o": 61817,
  "facebook": 61818,
  "fasterfind": 61819,
  "field-add": 61820,
  "field-dropdown": 61821,
  "field-paragraph": 61822,
  "field-signature-text": 61823,
  "field-signature": 61824,
  "field-text": 61825,
  "field-textblock": 61826,
  "file": 61827,
  "filter": 61828,
  "flag": 61829,
  "flagged-email": 61830,
  "flower": 61831,
  "footprint": 61832,
  "funnel": 61833,
  "globe-o": 61834,
  "globe": 61835,
  "google": 61836,
  "hammer": 61837,
  "headset": 61838,
  "herefish": 61839,
  "hidden": 61840,
  "holiday": 61841,
  "home": 61842,
  "hourglass-bottom": 61843,
  "hourglass-middle": 61844,
  "hourglass-top": 61845,
  "i9": 61846,
  "ice-cream": 61847,
  "idea": 61848,
  "inactive": 61849,
  "inbound-call": 61850,
  "inbox": 61851,
  "industry": 61852,
  "info-o": 61853,
  "info": 61854,
  "interview": 61855,
  "invoice": 61856,
  "job-circle": 61857,
  "job-code": 61858,
  "job": 61859,
  "key": 61860,
  "layout": 61861,
  "lead-circle": 61862,
  "lead": 61863,
  "link": 61864,
  "linkedin-f": 61865,
  "linkedin-o": 61866,
  "linkedin": 61867,
  "list-o": 61868,
  "list": 61869,
  "location-o": 61870,
  "location": 61871,
  "lock": 61872,
  "logout": 61873,
  "map": 61874,
  "menu-o": 61875,
  "menu": 61876,
  "missed-call": 61877,
  "mobile": 61878,
  "more": 61879,
  "morning-1": 61880,
  "morning-2": 61881,
  "morning-3": 61882,
  "morning": 61883,
  "move": 61884,
  "music": 61885,
  "news": 61886,
  "next": 61887,
  "night": 61888,
  "no-data": 61889,
  "non-payroll": 61890,
  "note": 61891,
  "notes": 61892,
  "nps": 61893,
  "occupation": 61894,
  "offer": 61895,
  "onboarding-365": 61896,
  "onboarding": 61897,
  "opportunity-circle": 61898,
  "opportunity": 61899,
  "organize": 61900,
  "outbound-call": 61901,
  "outbound-email": 61902,
  "overnight": 61903,
  "overview": 61904,
  "packets": 61905,
  "payable-charge": 61906,
  "payable": 61907,
  "payroll": 61908,
  "person-circle": 61909,
  "person": 61910,
  "phone": 61911,
  "pin": 61912,
  "plus": 61913,
  "preview": 61914,
  "previous": 61915,
  "print": 61916,
  "projects-square": 61917,
  "projects": 61918,
  "publish": 61919,
  "pulse": 61920,
  "puzzle": 61921,
  "question-o": 61922,
  "question": 61923,
  "radio-empty": 61924,
  "radio-filled": 61925,
  "rate-circle": 61926,
  "rate-filled": 61927,
  "rate-request": 61928,
  "rate-rule": 61929,
  "rate": 61930,
  "receivables": 61931,
  "refresh-o": 61932,
  "refresh": 61933,
  "rent": 61934,
  "reply": 61935,
  "report-code": 61936,
  "report": 61937,
  "republish": 61938,
  "resume": 61939,
  "rocket": 61940,
  "rules-config": 61941,
  "sailboat": 61942,
  "save": 61943,
  "search-menu": 61944,
  "search-question": 61945,
  "search": 61946,
  "section": 61947,
  "send": 61948,
  "sendout": 61949,
  "settings": 61950,
  "share-o": 61951,
  "share": 61952,
  "shield": 61953,
  "shipping-box": 61954,
  "slideout": 61955,
  "sms": 61956,
  "sort-asc": 61957,
  "sort-desc": 61958,
  "sortable": 61959,
  "source": 61960,
  "star-circle": 61961,
  "star-o-circle": 61962,
  "star-o": 61963,
  "star": 61964,
  "stethoscope": 61965,
  "stop-light": 61966,
  "tab": 61967,
  "tearsheet": 61968,
  "tie": 61969,
  "times": 61970,
  "timetable": 61971,
  "tools": 61972,
  "tower": 61973,
  "trending-down": 61974,
  "trending-up": 61975,
  "truck": 61976,
  "twitter-f": 61977,
  "twitter-o": 61978,
  "twitter": 61979,
  "umbrella": 61980,
  "unit": 61981,
  "upload": 61982,
  "user-o": 61983,
  "user": 61984,
  "users": 61985,
  "vendor": 61986,
  "view-list": 61987,
  "view-module": 61988,
  "viewall": 61989,
  "workflow": 61990,
  "x": 61991
}